<root><sentence>The professor highly recommends the student because he appreciates an inquisitive mind.</sentence><variables><key belong="appreciate.9" indexOfPlace="8" name="?he"><ref>The_professor</ref></key></variables><verb><recommend belong="because.7" indexOfPlace="4" isNegative="False" isleft="False"><source>propbank</source><wordInSentence>recommends</wordInSentence><thematicRoles><arg0><role>pag</role><content>The_professor</content></arg0><arg1><role>vsp</role><content>the_student</content></arg1></thematicRoles></recommend><appreciate belong="because.7" indexOfPlace="9" isNegative="False" isleft="True"><source>propbank</source><wordInSentence>appreciates</wordInSentence><thematicRoles><arg0><role>ppt</role><content>?he</content></arg0><arg1><role>pag</role><content>an_inquisitive_mind</content></arg1></thematicRoles></appreciate></verb><conjunction><because indexOfPlace="7"><thematic>(Causal,Cause,Effect)</thematic></because></conjunction><translate>because(appreciates(?he,an_inquisitive_mind),recommends(The_professor,the_student))</translate></root>