<root><Sentence>John called Bill because he needed someone to talk to.</Sentence><Variable><key Belong="need.6" Index="5" Name="?he"><ref>John</ref></key></Variable><Verb><call Belong="because.4" Index="2" IsNegative="False" Isleft="False"><source>propbank</source><wordInSentence>called</wordInSentence><thematicRoles><arg0><role>pag</role><content>John</content></arg0><arg1><role>ppt</role><content>Bill</content></arg1></thematicRoles></call><need Belong="because.4" Index="6" IsNegative="False" Isleft="True"><source>propbank</source><wordInSentence>needed</wordInSentence><thematicRoles><arg0><role>PAG</role><content>?he</content></arg0><arg1><role>ppt</role><content>someone</content></arg1></thematicRoles></need></Verb><Conjunction><because Index="4"><thematic>(Causation,Cause,Effect)</thematic></because></Conjunction><Representation>because(needed(?he,someone),called(John,Bill))</Representation></root>