<root><sentence>Americans preferred Obama to McCain because he chose Sarah Palin as his running-mate.</sentence><variables><key belong="as.11" indexOfPlace="12" name="?his_running-mate"><ref /></key><key belong="choose.8" indexOfPlace="7" name="?he"><ref>Obama</ref></key></variables><verb><choose belong="because.6" indexOfPlace="8" isNegative="False" isleft="True"><source>propbank</source><wordInSentence>chose</wordInSentence><thematicRoles><arg0><role>pag</role><content>?he</content></arg0><arg1><role>ppt</role><content>as(Sarah_Palin,?his_running-mate)</content></arg1></thematicRoles></choose><prefer belong="because.6" indexOfPlace="2" isNegative="False" isleft="False"><source>propbank</source><wordInSentence>preferred</wordInSentence><thematicRoles><arg0><role>pag</role><content>Americans</content></arg0><arg1><role>ppt</role><content>Obama</content></arg1><arg2><role>ppt</role><content>McCain</content></arg2></thematicRoles></prefer></verb><conjunction><as indexOfPlace="11"><thematic>(compare,sameDegree,sameDegree)</thematic></as><because indexOfPlace="6"><thematic>(Causal,Cause,Effect)</thematic></because></conjunction><translate>because(chose(?he,as(Sarah_Palin,?his_running-mate)),preferred(Americans,Obama,McCain))</translate></root>